service/__init__.py
service/calculate/__init__.py
service/calculate/profit.py
service/date/__init__.py
service/date/date.py
service/db/__init__.py
service/db/db.py
service/format/__init__.py
service/format/format.py
tests/__init__.py
quantservice-0.0.13.dist-info/LICENSE
quantservice-0.0.13.dist-info/METADATA
quantservice-0.0.13.dist-info/WHEEL
quantservice-0.0.13.dist-info/top_level.txt
quantservice-0.0.13.dist-info/RECORD
